{
  "name": "Big Data Visualisation",
  "children": [{
    "name": "Machine Learning",
    "children": [{
      "name": "Algorithms",
      "children": [{
        "name": "Receiver operating characteristic (ROC)",
        "size": 3938
      }, {
        "name": "Precision and Recall",
        "size": 3812
      }]
    }, {
      "name": "Classifiers",
      "children": [{
        "name": "Classification Error",
        "size": 3534,
        "children": [{
          "name": "Type I Error",
          "size": 3534,
          "pdf":"Erroneously added to the category"
        }, {
          "name": "Type II Error",
          "size": 5731,
          "pdf":"Missing or Undetected in a category"
        }]
      }, {
        "name": "Measuring Classification Error",
        "size": 5731
      }]
    }]
  }, {
    "name": "Uncertainty and Trust",
    "children": [{
      "name": "Uncertainty Propagation",
      "size": 17010,
      "children": [{
        "name": "Data Provenance(System)",
        "size": 1983
      },{
        "name": "Analytic Provenance(Human)"
      }]
    },{
      "name": "Trust Models",
      "children": [{
        "name": "5X5X5 Trust Model",
        "size": 1983
      }, {
        "name": "Goldstein Scale",
        "size": 2047
      }, {
        "name": "5W's",
        "size": 1375
      }]
    },{
      "name": "Viz",
      "children": [{
        "name": "Fuzziness and Location",
        "size": 1983
      }, {
        "name": "Value and Arrangement",
        "size": 2047
      }, {
        "name": "Size and Transparency",
        "size": 1375
      }, {
        "name": "Saturation and Hue",
        "size": 1375
      }]
    }]
  }, {
    "name": "Data",
    "children": [{
      "name": "DataSet",
      "size": 586,
      "children":[{
        "name":"GDELT",
        "size": 2200,
        "pdf":"Global Data on Events, Location and Tone",
        "children": [{
          "name": "Geospatial data",
          "size": 721
        }, {
          "name": "Unstructured Data",
          "size": 4294
        }, {
          "name": "Structured Data",
          "size": 9800
        }]
      }]
    }, {
      "name": "Document Store",
      "size": 3331,
      "children":[{
        "name":"Mongo",
        "size": 2200
      },{
        "name":"Elastic Search",
        "size": 2200
      }]
    }, {
        "name": "Document Store",
        "size": 3331
      }, {
      "name": "Data Ingestion & Transformation",
      "size": 3331,
      "children":[{
        "name":"Hadoop",
        "size": 2200,
        "children": [{
          "name": "HDFS",
          "size": 721
        }, {
          "name": "HBase",
          "size": 4294
        }]
      },{
        "name":"Google BigQuery",
        "size": 2200
      }]
    }]
  }, {
    "name": "Current Tools",
    "children": [{
      "name": "Tableau",
      "size": 8833
    }, {
      "name": "TimeSet",
      "size": 1732
    }, {
      "name": "SenseMap",
      "size": 3623
    }, {
      "name": "Nanocubes by AT&T",
      "size": 10066
    },
      {
        "name": "I2 by IBM ",
        "size": 10066
      }]
  }, {
    "name": "Application Focus Area",
    "children": [{
      "name": "Defence and Security Analytics ",
      "size": 4116,
      "children":[{
        "name":"Mass",
        "size":4000
      },{
        "name":"UKDSC",
        "size":4000
      },{
        "name":"Exo-Informatics",
        "size":4000
      }]
    },{
      "name":"Traffic Data",
      "size":3000
    }]
  }]
}
